[
	{
		"id":"41",
		"src":"images/meatImage/1.jpg",		
		"title":"恒都 羔羊后腿",		
		"price":"￥99"	
	},
	{
		"id":"42",
		"src":"images/meatImage/2.jpg",		
		"title":"名家厨房牛排",		
		"price":"￥108"
	
	},
	{
		"id":"43",
		"src":"images/meatImage/3.jpg",		
		"title":"双汇 猪脊骨块 ",	
		"price":"￥46"
	
	},
	{
		"id":"44",
		"src":"images/meatImage/4.jpg",		
		"title":"恒都澳洲菲力西冷牛排",	
		"price":"￥88"
	
	},
	{
		"id":"45",
		"src":"images/meatImage/5.jpg",		
		"title":"双汇猪尾",	
		"price":"￥54"
	
	},
	{
		"id":"46",
		"src":"images/meatImage/6.jpg",		
		"title":"双汇猪耳",	
		"price":"￥48"
	
	},
	{
		"id":"47",
		"src":"images/meatImage/7.jpg",		
		"title":"名家厨房澳洲菲 制牛排",	
		"price":"￥79"
	
	},
	{
		"id":"48",
		"src":"images/meatImage/8.jpg",		
		"title":"精气神猪通脊猪扒",		
		"price":"￥42"
	
	},
	{
		"id":"49",
		"src":"images/meatImage/9.jpg",		
		"title":"精气神猪前肩梅花肉",		
		"price":"￥46"
	
	},
	{
		"id":"50",
		"src":"images/meatImage/10.jpg",		
		"title":"双汇冰鲜猪肋排",		
		"price":"￥39"
	
	},
	{
		"id":"51",
		"src":"images/meatImage/11.jpg",		
		"title":"双汇冰鲜猪带筋猪蹄",		
		"price":"￥49"
	
	},
	{
		"id":"52",
		"src":"images/meatImage/12.jpg",		
		"title":"荷兰进口猪肋排条",		
		"price":"￥59"
	
	},
	{
		"id":"53",
		"src":"images/meatImage/13.jpg",		
		"title":"阿都沁菲力牛排套餐",		
		"price":"￥69"
	
	},
	{
		"id":"54",
		"src":"images/meatImage/14.jpg",		
		"title":"加拿大进口猪肋排条",		
		"price":"￥68"
	
	},
	{
		"id":"55",
		"src":"images/meatImage/15.jpg",		
		"title":"顺鑫鑫源牛腱子",		
		"price":"￥68"
	
	},
	{
		"id":"56",
		"src":"images/meatImage/16.jpg",		
		"title":"恒都牛腩",		
		"price":"￥59"
	
	},
	{
		"id":"57",
		"src":"images/meatImage/17.jpg",		
		"title":"恒都澳洲牛排套餐",		
		"price":"￥99"
	
	},
	{
		"id":"58",
		"src":"images/meatImage/18.jpg",		
		"title":"新西兰特修金钱腱",		
		"price":"￥99"
	
	},
	{
		"id":"59",
		"src":"images/meatImage/19.jpg",		
		"title":"鲜农乐冷鲜猪排骨",		
		"price":"￥58"
	
	},
	{
		"id":"60",
		"src":"images/meatImage/20.jpg",		
		"title":"得利斯猪肚",		
		"price":"￥60"
	
	}
	
	
]
